desktop_use/__init__.py
desktop_use/client.py
desktop_use/exceptions.py
desktop_use/models.py
desktop_use-0.1.3.dist-info/METADATA
desktop_use-0.1.3.dist-info/WHEEL
desktop_use-0.1.3.dist-info/top_level.txt
desktop_use-0.1.3.dist-info/RECORD
